setup.cfg
setup.py
aiohttp_healthcheck/__init__.py
aiohttp_healthcheck.egg-info/PKG-INFO
aiohttp_healthcheck.egg-info/SOURCES.txt
aiohttp_healthcheck.egg-info/dependency_links.txt
aiohttp_healthcheck.egg-info/requires.txt
aiohttp_healthcheck.egg-info/top_level.txt
aiohttp_healthcheck.egg-info/zip-safe