Metadata-Version: 1.1
Name: aiohttp-healthcheck
Version: 1.3.1
Summary: Adds healthcheck endpoints to aiohttp apps. Based on https://github.com/Runscope/healthcheck.
Home-page: https://github.com/brannon/aiohttp-healthcheck
Author: Brannon Jones
Author-email: brannonj@gmail.com
License: MIT
Platform: any
Classifier: Development Status :: 5 - Production/Stable
Classifier: Environment :: Web Environment
Classifier: Programming Language :: Python
Classifier: Programming Language :: Python :: 3
Classifier: Programming Language :: Python :: 3.4
Classifier: Programming Language :: Python :: 3.5
